cppstream/__init__.py
cppstream/_in/__init__.py
cppstream/_in/cin.py
cppstream/_in/fin.py
cppstream/_in/in.py
cppstream/_in/string.py
cppstream/_out/__init__.py
cppstream/_out/cout.py
cppstream/_out/fout.py
cppstream/_out/out.py
cppstream/_out/string.py
cppstream/base.py
cppstream/endl.py
cppstream/in/__init__.py
cppstream/out/__init__.py
cppstream-0.1.0.dist-info/LICENSE
cppstream-0.1.0.dist-info/WHEEL
cppstream-0.1.0.dist-info/METADATA
cppstream-0.1.0.dist-info/RECORD
